juselara_qtile/__init__.py
juselara_qtile/dataclasses.py
juselara_qtile/generals.py
juselara_qtile/keys.py
juselara_qtile-0.1.6.dist-info/WHEEL
juselara_qtile-0.1.6.dist-info/METADATA
juselara_qtile-0.1.6.dist-info/RECORD
