Metadata-Version: 2.1
Name: juselara-qtile
Version: 0.1.6
Summary: My setup for the Qtile window manager
License: MIT
Author: Juan Lara
Author-email: julara@unal.edu.co
Requires-Python: >3.8,<3.11
Classifier: License :: OSI Approved :: MIT License
Classifier: Programming Language :: Python :: 3
Classifier: Programming Language :: Python :: 3.10
Classifier: Programming Language :: Python :: 3.9
Requires-Dist: cairocffi (>=1.3.0,<2.0.0)
Requires-Dist: cffi (>=1.15.0,<2.0.0)
Requires-Dist: psutil (>=5.9.0,<6.0.0)
Requires-Dist: pydantic (>=1.9.0,<2.0.0)
Requires-Dist: qtile (>=0.21.0,<0.22.0)
Requires-Dist: xcffib (>=0.11.1,<0.12.0)
Requires-Dist: yacmmal (>=0.1.6,<0.2.0)
